image_datasets/__init__.py
image_datasets/core.py
image_datasets/datasets.py
image_datasets-0.0.7.dist-info/METADATA
image_datasets-0.0.7.dist-info/WHEEL
image_datasets-0.0.7.dist-info/top_level.txt
image_datasets-0.0.7.dist-info/RECORD
